odoo/addons/product_sticker/README.rst
odoo/addons/product_sticker/__init__.py
odoo/addons/product_sticker/__manifest__.py
odoo/addons/product_sticker/data/menus.xml
odoo/addons/product_sticker/i18n/es.po
odoo/addons/product_sticker/i18n/it.po
odoo/addons/product_sticker/i18n/product_sticker.pot
odoo/addons/product_sticker/models/__init__.py
odoo/addons/product_sticker/models/product_attribute.py
odoo/addons/product_sticker/models/product_attribute_value.py
odoo/addons/product_sticker/models/product_product.py
odoo/addons/product_sticker/models/product_sticker.py
odoo/addons/product_sticker/models/product_sticker_mixin.py
odoo/addons/product_sticker/models/product_template.py
odoo/addons/product_sticker/readme/CONTRIBUTORS.md
odoo/addons/product_sticker/readme/DESCRIPTION.md
odoo/addons/product_sticker/readme/USAGE.md
odoo/addons/product_sticker/security/ir.model.access.csv
odoo/addons/product_sticker/static/description/icon.png
odoo/addons/product_sticker/static/description/index.html
odoo/addons/product_sticker/tests/__init__.py
odoo/addons/product_sticker/tests/common.py
odoo/addons/product_sticker/tests/test_product.py
odoo/addons/product_sticker/views/product_attribute_views.xml
odoo/addons/product_sticker/views/product_product_views.xml
odoo/addons/product_sticker/views/product_sticker_views.xml
odoo/addons/product_sticker/views/product_template_views.xml
odoo_addon_product_sticker-18.0.1.0.2.1.dist-info/METADATA
odoo_addon_product_sticker-18.0.1.0.2.1.dist-info/WHEEL
odoo_addon_product_sticker-18.0.1.0.2.1.dist-info/top_level.txt
odoo_addon_product_sticker-18.0.1.0.2.1.dist-info/RECORD
