Metadata-Version: 2.1
Name: odoo-addon-product_sticker
Version: 18.0.1.0.2.1
Requires-Python: >=3.10
Requires-Dist: odoo==18.0.*
Summary: Product Sticker
Home-page: https://github.com/OCA/product-attribute
License: LGPL-3
Author: Moduon, Odoo Community Association (OCA)
Author-email: support@odoo-community.org
Classifier: Programming Language :: Python
Classifier: Framework :: Odoo
Classifier: Framework :: Odoo :: 18.0
Classifier: License :: OSI Approved :: GNU Lesser General Public License v3 (LGPLv3)
